setup.py
cjtmc_base/__init__.py
cjtmc_base/admin.py
cjtmc_base/apps.py
cjtmc_base/management.py
cjtmc_base/models.py
cjtmc_base/select.py
cjtmc_base/tests.py
cjtmc_base/urls.py
cjtmc_base/views.py
cjtmc_base.egg-info/PKG-INFO
cjtmc_base.egg-info/SOURCES.txt
cjtmc_base.egg-info/dependency_links.txt
cjtmc_base.egg-info/not-zip-safe
cjtmc_base.egg-info/requires.txt
cjtmc_base.egg-info/top_level.txt
cjtmc_base/api/__init__.py
cjtmc_base/api/all.py
cjtmc_base/base/__init__.py
cjtmc_base/base/serializer.py
cjtmc_base/base/urls.py
cjtmc_base/base/views.py
cjtmc_base/migrations/0001_initial.py
cjtmc_base/migrations/0002_env.py
cjtmc_base/migrations/0003_env_siteid.py
cjtmc_base/migrations/0004_idc_remark.py
cjtmc_base/migrations/0005_auto_20220414_0853.py
cjtmc_base/migrations/0006_origin_default.py
cjtmc_base/migrations/__init__.py
cjtmc_base/sdk/__init__.py
cjtmc_base/sdk/ali/__init__.py
cjtmc_base/sdk/ali/base.py
cjtmc_base/sdk/ali/regions.py
cjtmc_base/sdk/huawei/__init__.py
cjtmc_base/sdk/huawei/base.py
cjtmc_base/sdk/huawei/regions.py
cjtmc_base/sdk/openstack/__init__.py
cjtmc_base/sdk/openstack/base.py
cjtmc_base/sdk/openstack/regions.py
cjtmc_base/sdk/tencent/__init__.py
cjtmc_base/sdk/tencent/base.py
cjtmc_base/sdk/tencent/regions.py
cjtmc_base/sdk/vmware/__init__.py
cjtmc_base/sdk/vmware/base.py
cjtmc_base/sdk/vmware/regions.py
cjtmc_base/sdk/vmware/tools/__init__.py
cjtmc_base/sdk/vmware/tools/add_nic_to_vm.py
cjtmc_base/sdk/vmware/tools/alarm.py
cjtmc_base/sdk/vmware/tools/cli.py
cjtmc_base/sdk/vmware/tools/cluster.py
cjtmc_base/sdk/vmware/tools/datacenter.py
cjtmc_base/sdk/vmware/tools/disk.py
cjtmc_base/sdk/vmware/tools/interactive_wrapper.py
cjtmc_base/sdk/vmware/tools/pbmhelper.py
cjtmc_base/sdk/vmware/tools/pchelper.py
cjtmc_base/sdk/vmware/tools/service_instance.py
cjtmc_base/sdk/vmware/tools/serviceutil.py
cjtmc_base/sdk/vmware/tools/snapshot_operations.py
cjtmc_base/sdk/vmware/tools/tasks.py
cjtmc_base/sdk/vmware/tools/vm.py
cjtmc_base/sdk/zstack/__init__.py
cjtmc_base/sdk/zstack/base.py
cjtmc_base/sdk/zstack/regions.py
cjtmc_base/tasks/__init__.py
cjtmc_base/tasks/resources.py
cjtmc_base/utils/__init__.py
cjtmc_base/utils/chanjetrs.py
